ptir/__init__.py
ptir-1.2.1.dist-info/LICENSE
ptir-1.2.1.dist-info/METADATA
ptir-1.2.1.dist-info/WHEEL
ptir-1.2.1.dist-info/top_level.txt
ptir-1.2.1.dist-info/RECORD
