Metadata-Version: 2.1
Name: ptir
Version: 1.2.1
Summary: Python Terminal Image Renderer
Home-page: https://github.com/JoshuaBragg/PTIR
Author: Joshua Bragg
Author-email: joshua.bragg@outlook.com
License: MIT
Platform: UNKNOWN
Classifier: Programming Language :: Python :: 3
Classifier: License :: OSI Approved :: MIT License
Classifier: Operating System :: OS Independent
Requires-Dist: Pillow
Requires-Dist: numpy
